Metadata-Version: 2.1
Name: modeval
Version: 1.5
Summary: Pure Python modular math evaluater without using built-in eval() and no dependencies.
Home-page: https://github.com/diquah/modeval/tree/v1.5
Author: Diquah
License: MIT
Download-URL: https://github.com/diquah/modeval/archive/refs/tags/v1.5.tar.gz
Keywords: eval,expression,parser,math,string,modular
Platform: UNKNOWN
Classifier: Development Status :: 5 - Production/Stable
Classifier: Intended Audience :: Developers
Classifier: License :: OSI Approved :: MIT License
Classifier: Programming Language :: Python :: 3
Classifier: Programming Language :: Python :: 3.7
Classifier: Programming Language :: Python :: 3.10
Requires-Python: >=3.7
License-File: LICENSE
